calculus_learn_kit-1.0.4.dist-info/licenses/LICENSE
src/__init__.py
src/basic_rules_core.py
src/basic_rules_viz.py
src/derivatives_core.py
src/derivatives_viz.py
src/fundamental_theorem_core.py
src/fundamental_theorem_viz.py
src/integrals_core.py
src/integrals_viz.py
src/main.py
calculus_learn_kit-1.0.4.dist-info/METADATA
calculus_learn_kit-1.0.4.dist-info/WHEEL
calculus_learn_kit-1.0.4.dist-info/entry_points.txt
calculus_learn_kit-1.0.4.dist-info/top_level.txt
calculus_learn_kit-1.0.4.dist-info/RECORD
