Metadata-Version: 2.4
Name: calculus-learn-kit
Version: 1.0.4
Summary: A comprehensive toolkit for learning and visualizing calculus concepts
Author: Abdullah Barrak, Claude Sonnet 4
License: MIT
Project-URL: Homepage, https://github.com/abarrak/calculus.py
Project-URL: Bug Reports, https://github.com/abarrak/calculus.py/issues
Project-URL: Source, https://github.com/abarrak/calculus.py
Project-URL: Documentation, https://github.com/abarrak/calculus.py#readme
Keywords: calculus,mathematics,education,visualization,derivatives,integrals,matplotlib
Classifier: Development Status :: 4 - Beta
Classifier: Intended Audience :: Education
Classifier: Intended Audience :: Science/Research
Classifier: License :: OSI Approved :: MIT License
Classifier: Operating System :: OS Independent
Classifier: Programming Language :: Python :: 3
Classifier: Programming Language :: Python :: 3.8
Classifier: Programming Language :: Python :: 3.9
Classifier: Programming Language :: Python :: 3.10
Classifier: Programming Language :: Python :: 3.11
Classifier: Programming Language :: Python :: 3.12
Classifier: Topic :: Education
Classifier: Topic :: Scientific/Engineering :: Mathematics
Classifier: Topic :: Scientific/Engineering :: Visualization
Requires-Python: >=3.8
License-File: LICENSE
Requires-Dist: numpy>=1.20.0
Requires-Dist: matplotlib>=3.5.0
Requires-Dist: sympy>=1.9.0
Requires-Dist: scipy>=1.7.0
Provides-Extra: dev
Requires-Dist: pytest>=6.0; extra == "dev"
Requires-Dist: pytest-mock; extra == "dev"
Requires-Dist: autopep8; extra == "dev"
Requires-Dist: flake8; extra == "dev"
Provides-Extra: jupyter
Requires-Dist: jupyter>=1.0.0; extra == "jupyter"
Requires-Dist: ipython>=7.23.1; extra == "jupyter"
Requires-Dist: notebook>=6.0.3; extra == "jupyter"
Dynamic: license-file
